Metadata-Version: 2.1
Name: mxnet-octave-conv
Version: 0.1.0
Summary: Octave convolution
Home-page: https://github.com/CyberZHG/mxnet-octave-conv
Author: CyberZHG
Author-email: CyberZHG@gmail.com
License: Anti 996
Platform: UNKNOWN
Classifier: Programming Language :: Python :: 2.7
Classifier: Programming Language :: Python :: 3.6
Classifier: License :: Other/Proprietary License
Classifier: Operating System :: OS Independent
